{
"en": {
    "build":"build",
    "put":"put",
    "peg": "peg",
    "pick": "pick",
    "point": "point",
    "take":"take",
    "give": "give",
    "pass": "pass",
    "glue": "glue",
    "learn_new_task": "Learn a new task",
    "learn_new_tower": "Learn a new tower",
    "demonstration": "Demonstration",
    "define_area": "Define area",
    "remove_product": "Remove product",
    "define": "define",
    "put that": "put that",
    "give that": "give that",
    "tidy that": "tidy that",
    "cube": "cube",
    "any": "any",
    "red":"red",
    "red wine": "red wine",
    "dark red": "dark red",
    "magenta": "magenta",
    "blue": "blue",
    "light blue": "light blue",
    "cyan": "cyan",
    "green": "green",
    "black": "black",
    "yellow": "yellow",
    "gold": "gold",
    "purple": "purple",
    "dark purple": "dark purple",
    "white": "white",
    "here": "here",
    "down": "down",
    "position": "position",
    "center": "center",
    "left": "left",
    "right":"right",
    "top": "top",
    "bottom": "bottom",
    "and": "and",
    "tidy": "tidy",
    "silent": "silent",
    "talk": "talk",
    "storage": "storage",
    "define_storage": "Define storage",
    "remove_command": "Cancel command",
    "remove_last_command": "Cancel last command",
    "build_assembly": "Build",
    "backstage": "backstage",
    "table": "table",
    "all": "all",
    "release": "release",
    "stop": "stop",
    "cancel_build": "Cancel building",
    "cancel":"cancel"
    },
"cs": {
    "build":"stavět",
    "put":"polož",
    "peg": "kolík",
    "pick": "seber",
    "point": "ukaž",
    "take": "vezmi",
    "give": "podej",
    "pass": "pass",
    "glue": "nalep",
    "learn_new_task": "Nauč se novou úlohu",
    "learn_new_tower": "Nauč se novou věž",
    "demonstration": "Demonstrace",
    "define_area": "Definování oblasti",
    "define": "definuj",
    "build_assembly": "Postav",
    "remove_product": "Odeber výrobek",
    "put that": "polož to",
    "give that": "podej to",
    "tidy that": "ukliď to",
    "cube": "kostka",
    "any": "jakoukoli",
    "red":"červená",
    "red wine": "vínová",
    "dark red": "vínová",
    "magenta": "růžová",
    "blue": "modrá",
    "light blue": "světle modrá",
    "cyan": "tyrkysová",
    "green": "zelená",
    "black": "černá",
    "purple": "fialová",
    "dark purple": "tmavě fialová",
    "yellow": "žlutá",
    "gold": "zlatá",
    "white": "bílá",
    "here": "sem",
    "down": "dolů",
    "position": "pozice",
    "center": "center",
    "left": "vlevo",
    "right":"vpravo",
    "top": "nad",
    "bottom": "pod",
    "and": "a",
    "tidy": "ukliď",
    "silent": "ticho",
    "talk": "mluv",
    "storage": "úložiště",
    "define_storage": "Definuj úložiště",
    "define_position": "Definuj pozici",
    "remove_last_command": "Zruš poslední příkaz",
    "remove_command": "Zruš příkaz",
    "backstage": "sklad",
    "table": "stůl",
    "all": "vše",
    "release": "pustit",
    "stop": "stop",
    "cancel_build": "zruš stavění",
    "cancel":"zruš"
}
      }